code_periscope/__init__.py
code_periscope/__main__.py
code_periscope/cli.py
code_periscope/core/__init__.py
code_periscope/core/__main__.py
code_periscope/core/cli.py
code_periscope/core/pipeline.py
code_periscope/core/repo.py
code_periscope/core/report_model.py
code_periscope/core/signals.py
code_periscope/core/classify/__init__.py
code_periscope/core/classify/commit_type.py
code_periscope/core/classify/overlay_tags.py
code_periscope/core/cluster/__init__.py
code_periscope/core/cluster/kmeans.py
code_periscope/core/cluster/labeling.py
code_periscope/core/features/__init__.py
code_periscope/core/features/metrics.py
code_periscope/core/features/trends.py
code_periscope/core/ingest/__init__.py
code_periscope/core/ingest/git_history.py
code_periscope/core/risk/__init__.py
code_periscope/core/risk/explanations.py
code_periscope/core/risk/scoring.py
code_periscope/renderers/__init__.py
code_periscope/renderers/html.py
code_periscope/renderers/markdown.py
code_periscope-0.2.0.dist-info/licenses/LICENSE
code_periscope-0.2.0.dist-info/METADATA
code_periscope-0.2.0.dist-info/WHEEL
code_periscope-0.2.0.dist-info/entry_points.txt
code_periscope-0.2.0.dist-info/top_level.txt
code_periscope-0.2.0.dist-info/RECORD
