Metadata-Version: 2.4
Name: code-periscope
Version: 0.2.0
Summary: Repository risk analysis tool (Code Periscope).
Author: Code Periscope contributors
License: MIT
Requires-Python: >=3.11
License-File: LICENSE
Requires-Dist: pandas>=2.2
Requires-Dist: numpy>=2.1
Requires-Dist: scikit-learn>=1.5
Requires-Dist: GitPython>=3.1
Requires-Dist: pydantic>=2.8
Requires-Dist: typer>=0.12
Requires-Dist: rich>=13.9
Provides-Extra: test
Requires-Dist: pytest>=8; extra == "test"
Requires-Dist: pytest-cov>=5; extra == "test"
Requires-Dist: coverage>=7; extra == "test"
Dynamic: license-file
